muphyn/__init__.py
muphyn/__main__.py
muphyn/runner.py
muphyn/assets/MuPhyN.ico
muphyn/assets/MuPhyN.svg
muphyn/assets/MuPhyN_Logo_animation.css
muphyn/assets/__init__.py
muphyn/assets/splashscreen.png
muphyn/assets/splashscreen_project.kra
muphyn/assets/BoxIcons/addition.svg
muphyn/assets/BoxIcons/band_pass_filter.svg
muphyn/assets/BoxIcons/constant.svg
muphyn/assets/BoxIcons/derivator.svg
muphyn/assets/BoxIcons/divide.svg
muphyn/assets/BoxIcons/graph.svg
muphyn/assets/BoxIcons/high_pass_filter.svg
muphyn/assets/BoxIcons/impulse.svg
muphyn/assets/BoxIcons/integrator.svg
muphyn/assets/BoxIcons/logarithm.svg
muphyn/assets/BoxIcons/low_pass_filter.svg
muphyn/assets/BoxIcons/multiplication.svg
muphyn/assets/BoxIcons/noise.svg
muphyn/assets/BoxIcons/notch_filter.svg
muphyn/assets/BoxIcons/omlogosmall.svg
muphyn/assets/BoxIcons/ramp.svg
muphyn/assets/BoxIcons/saw_tooth.svg
muphyn/assets/BoxIcons/sine.svg
muphyn/assets/BoxIcons/square.svg
muphyn/assets/BoxIcons/step.svg
muphyn/assets/BoxIcons/TestBoxIcon/BoxParameterWidgetsTest.svg
muphyn/assets/BoxIcons/TestBoxIcon/InfiniteInputTest.svg
muphyn/assets/BoxIcons/TestBoxIcon/InfiniteOutputTest.svg
muphyn/assets/Components/Electrics/capacitor.svg
muphyn/assets/Components/Electrics/conductor.svg
muphyn/assets/Components/Electrics/constant_current_source.svg
muphyn/assets/Components/Electrics/constant_voltage_source.svg
muphyn/assets/Components/Electrics/cosine_current_source.svg
muphyn/assets/Components/Electrics/cosine_voltage_source.svg
muphyn/assets/Components/Electrics/exp_cosine_current_source.svg
muphyn/assets/Components/Electrics/exp_cosine_voltage_source.svg
muphyn/assets/Components/Electrics/exp_sine_current_source.svg
muphyn/assets/Components/Electrics/exp_sine_voltage_source.svg
muphyn/assets/Components/Electrics/ground.svg
muphyn/assets/Components/Electrics/gyrator.svg
muphyn/assets/Components/Electrics/inductor.svg
muphyn/assets/Components/Electrics/n_transformer.svg
MuPhyN-0.1.2.post1.dist-info/LICENSE
MuPhyN-0.1.2.post1.dist-info/METADATA
MuPhyN-0.1.2.post1.dist-info/WHEEL
MuPhyN-0.1.2.post1.dist-info/top_level.txt
MuPhyN-0.1.2.post1.dist-info/RECORD
