Metadata-Version: 2.2
Name: MuPhyN
Version: 0.1.2.post1
Summary: A graphical tool for modeling and simulating multi-physical systems.
Author-email: CeREF Technique <contact.tech@ceref.be>, Dylan Fievez <fievezd@ceref.be>, Francois Demoulin <francois.demoulin@outlook.be>, Thomas Herpoel <herpoelt@ceref.be>
Project-URL: Homepage, https://gitlab.com/CeREF/muphyn
Classifier: Programming Language :: Python :: 3
Classifier: License :: OSI Approved :: GNU Affero General Public License v3
Classifier: Operating System :: OS Independent
Requires-Python: >=3.9.13
License-File: LICENSE
Requires-Dist: packaging>=23.0
Requires-Dist: ipython>=7.31.1
Requires-Dist: Pillow>=9.2.0
Requires-Dist: PyYAML>=6.0
Requires-Dist: scipy>=1.10.0
Requires-Dist: PyQt6>=6.4.2
Requires-Dist: PyQt6-WebEngine>=6.4.0
Requires-Dist: PyQt6-QScintilla>=2.13.4
Requires-Dist: numexpr>=2.6.1
Requires-Dist: numpy>=1.21.5
Requires-Dist: matplotlib>=3.5.2
Requires-Dist: opcua>=0.98.13
Requires-Dist: OMPython>=3.4.0
Requires-Dist: pandas>=1.4.4
Requires-Dist: tables>=3.8.0
Requires-Dist: control>=0.9.4
